zenann/__init__.py
zenann/zenann.cpython-312-x86_64-linux-gnu.so
zenann-0.1.0.dist-info/METADATA
zenann-0.1.0.dist-info/WHEEL
zenann-0.1.0.dist-info/top_level.txt
zenann-0.1.0.dist-info/RECORD
