Metadata-Version: 2.4
Name: zenann
Version: 0.1.0
Summary: ZenANN: High-performance ANN search with a prebuilt C++ .so module
Author-email: Seco1024 <deyenqiu@gmail.com>
Project-URL: Homepage, https://github.com/Seco1024/zenann
Project-URL: Repository, https://github.com/Seco1024/zenann.git
Requires-Python: >=3.10
Requires-Dist: numpy>=1.20
Requires-Dist: pybind11>=2.10
